golemrpc/__init__.py
golemrpc/core_imports.py
golemrpc/remote_resources_provider.py
golemrpc/rpccomponent.py
golemrpc/transfermanager.py
golemrpc/utils.py
golemrpc/handlers/__init__.py
golemrpc/handlers/rpcexit.py
golemrpc/handlers/singlerpc.py
golemrpc/handlers/task.py
golemrpc/handlers/task_controller.py
golemrpc/schemas/__init__.py
golemrpc/schemas/tasks.py
golemrpc-0.3.6.dist-info/LICENSE
golemrpc-0.3.6.dist-info/METADATA
golemrpc-0.3.6.dist-info/WHEEL
golemrpc-0.3.6.dist-info/top_level.txt
golemrpc-0.3.6.dist-info/RECORD
