Metadata-Version: 2.1
Name: golemrpc
Version: 0.3.6
Summary: Golem RPC library
Home-page: http://github.com/golemfactory/raspa-poc
Author: Golem Team
Author-email: contact@golem.network
License: MIT
Platform: UNKNOWN
Requires-Dist: Automat (==0.7.0)
Requires-Dist: Twisted (==17.9.0)
Requires-Dist: appdirs (==1.4.3)
Requires-Dist: astroid (==2.1.0)
Requires-Dist: attrs (==18.2.0)
Requires-Dist: autobahn (==18.10.1)
Requires-Dist: cbor (==1.0.0)
Requires-Dist: cloudpickle (==0.6.1)
Requires-Dist: constantly (==15.1.0)
Requires-Dist: hyperlink (==18.0.0)
Requires-Dist: idna (==2.8)
Requires-Dist: incremental (==17.5.0)
Requires-Dist: isort (==4.3.4)
Requires-Dist: janus (==0.4.0)
Requires-Dist: lazy-object-proxy (==1.3.1)
Requires-Dist: marshmallow (==3.0.0rc3)
Requires-Dist: mccabe (==0.6.1)
Requires-Dist: pylint (==2.2.2)
Requires-Dist: six (==1.11.0)
Requires-Dist: txaio (==18.8.1)
Requires-Dist: typed-ast (==1.1.0)
Requires-Dist: u-msgpack-python (==2.5.0)
Requires-Dist: wrapt (==1.10.11)
Requires-Dist: zope.interface (==4.6.0)
